{"errors":[],"warnings":[],"namedChunkGroups":{"app":{"chunks":[8,7,3],"assets":["webpack-runtime-e90233a766fbb4ada26d.js","webpack-runtime-e90233a766fbb4ada26d.js.map","framework-f0b1095636d7eea85476.js","framework-f0b1095636d7eea85476.js.map","app-57145dd3bf1c8f4b1f0d.js","app-57145dd3bf1c8f4b1f0d.js.map"],"children":{},"childAssets":{}},"component---src-pages-404-js":{"chunks":[1,0,5],"assets":["styles.b947781388dd98b8ba88.css","styles-48fa8a050a65bb8447bd.js","styles-48fa8a050a65bb8447bd.js.map","commons-63770e49a62c4bef76c2.js","commons-63770e49a62c4bef76c2.js.map","component---src-pages-404-js-bcd96a9372bb0508869a.js","component---src-pages-404-js-bcd96a9372bb0508869a.js.map"],"children":{},"childAssets":{}},"component---src-pages-index-js":{"chunks":[1,2,4,0,6],"assets":["styles.b947781388dd98b8ba88.css","styles-48fa8a050a65bb8447bd.js","styles-48fa8a050a65bb8447bd.js.map","a9a7754c-4ea34b919f533368e2e5.js","a9a7754c-4ea34b919f533368e2e5.js.map","cb1608f2-f7acc6402d75105a9fd6.js","cb1608f2-f7acc6402d75105a9fd6.js.map","commons-63770e49a62c4bef76c2.js","commons-63770e49a62c4bef76c2.js.map","component---src-pages-index-js-29e96b7f57177505d038.js","component---src-pages-index-js-29e96b7f57177505d038.js.map"],"children":{},"childAssets":{}}},"assetsByChunkName":{"app":["webpack-runtime-e90233a766fbb4ada26d.js","framework-f0b1095636d7eea85476.js","app-57145dd3bf1c8f4b1f0d.js"],"component---src-pages-404-js":["styles.b947781388dd98b8ba88.css","styles-48fa8a050a65bb8447bd.js","commons-63770e49a62c4bef76c2.js","component---src-pages-404-js-bcd96a9372bb0508869a.js"],"component---src-pages-index-js":["styles.b947781388dd98b8ba88.css","styles-48fa8a050a65bb8447bd.js","a9a7754c-4ea34b919f533368e2e5.js","cb1608f2-f7acc6402d75105a9fd6.js","commons-63770e49a62c4bef76c2.js","component---src-pages-index-js-29e96b7f57177505d038.js"]}}